{
	"format_version": "1.12.0",
	"minecraft:geometry": [
		{
			"description": {
				"identifier": "geometry.scorpioidbloodluster",
				"texture_width": 128,
				"texture_height": 128,
				"visible_bounds_width": 9,
				"visible_bounds_height": 8,
				"visible_bounds_offset": [0, 3, 0]
			},
			"bones": [
				{
					"name": "full",
					"pivot": [0, 43.8611, -0.03059]
				},
				{
					"name": "torso",
					"parent": "full",
					"pivot": [0, 44.8611, -1.18059],
					"cubes": [
						{"origin": [-1.6, 35.8986, -1.16809], "size": [7.225, 1.525, 2.8], "pivot": [2, 39.0611, 0.11941], "rotation": [-2.5, 35, 0], "uv": [78, 48]},
						{"origin": [-1.6, 37.7986, -1.16809], "size": [8.425, 1.325, 2.8], "pivot": [2, 39.0611, 0.11941], "rotation": [-2.5, 35, 0], "uv": [75, 24]},
						{"origin": [-6.9, 35.8986, -1.16809], "size": [8.6, 1.55, 2.8], "pivot": [-1.9, 39.0611, 0.11941], "rotation": [-2.5, -35, 0], "uv": [75, 28]},
						{"origin": [-6.5, 37.7986, -1.16809], "size": [8.2, 1.35, 2.8], "pivot": [-1.9, 39.0611, 0.11941], "rotation": [-2.5, -35, 0], "uv": [74, 0]},
						{"origin": [-3.375, 36.4736, -0.69309], "size": [3.45, 6.925, 2.8], "pivot": [0, 39.0611, -0.85559], "rotation": [20.26156, -22.24398, -5.96915], "uv": [78, 40]},
						{"origin": [0.025, 36.4736, -1.99309], "size": [3.45, 6.85, 2.8], "pivot": [3.625, 39.0611, -0.85559], "rotation": [21.23219, 19.62364, 9.45605], "uv": [77, 76]},
						{"origin": [-3.05, 41.2736, -1.31809], "size": [6.1, 3.5, 2.45], "pivot": [0, 43.8611, -0.75559], "rotation": [5.70166, -1.47342, 1.48724], "uv": [74, 35]},
						{"origin": [-8.9, 40.1986, -0.64309], "size": [10.425, 3.1, 2.325], "pivot": [-1.9, 38.6611, 0.11941], "rotation": [10.09426, -33.77374, -22.10992], "uv": [71, 16]},
						{"origin": [-1.65, 36.4736, 0.40691], "size": [3.45, 4.775, 0.7], "pivot": [1.95, 39.0611, 0.11941], "rotation": [19.95166, -1.47342, 1.48724], "uv": [34, 86]},
						{"origin": [-1.375, 40.1236, -0.71809], "size": [9.425, 3.25, 2.6], "pivot": [1.9, 38.6611, 0.11941], "rotation": [9.26688, 33.98395, 20.62572], "uv": [0, 70]}
					]
				},
				{
					"name": "pincerL",
					"parent": "torso",
					"pivot": [3.00544, 42.76858, -1.75763],
					"cubes": [
						{"origin": [10.66794, 49.31858, -16.25763], "size": [8.825, 3.55, 2.85], "pivot": [15.38044, 56.09358, -14.13263], "rotation": [3.4272, 61.3696, 0.8485], "uv": [44, 54]},
						{"origin": [14.44294, 47.86858, -14.55763], "size": [6.8, 6.05, 2.75], "pivot": [15.38044, 54.34358, -14.13263], "rotation": [-37.6648, 75.4261, -47.0838], "uv": [16, 62]},
						{"origin": [14.99175, 46.12136, -29.94213], "size": [6.225, 0.6, 0.425], "pivot": [18.10425, 46.42136, -29.35463], "rotation": [85.52512, 71.12392, 90.87803], "uv": [18, 73]},
						{"origin": [15.05741, 46.74986, -29.82], "size": [6.225, 0.725, 0.375], "pivot": [18.16991, 47.11236, -29.2825], "rotation": [84.6884, 64.6762, 91.0128], "uv": [17, 68]},
						{"origin": [24.14294, 51.84358, -13.85763], "size": [6.225, 1.25, 0.675], "pivot": [15.38044, 56.09358, -14.13263], "rotation": [64.2936, 67.0851, 68.3457], "uv": [84, 31]},
						{"origin": [4.825, 38.0236, 0.73191], "size": [15.625, 3.05, 1.85], "pivot": [-0.6, 38.9611, 0.11941], "rotation": [-25.89398, 34.87873, -44.2848], "uv": [44, 2]},
						{"origin": [24.14294, 54.41858, -13.85763], "size": [6.225, 1.25, 0.675], "pivot": [15.38044, 56.09358, -14.13263], "rotation": [68.3691, 62.7315, 72.8422], "uv": [79, 75]},
						{"origin": [18.16794, 49.61858, -14.55763], "size": [6.225, 6.05, 2.475], "pivot": [15.38044, 56.09358, -14.13263], "rotation": [44.6165, 70.0074, 47.5261], "uv": [52, 59]}
					]
				},
				{
					"name": "wingl",
					"parent": "torso",
					"pivot": [-1.9, 45.4861, 0.11941],
					"cubes": [
						{
							"origin": [-15.90555, -29.41567, 0.37659],
							"size": [15.45, 75.525, 0.3],
							"pivot": [-1.875, 45.8611, 0.74441],
							"rotation": [58.64334, -29.78836, -27.95214],
							"uv": {
								"north": {"uv": [11, 0], "uv_size": [11, 57]},
								"east": {"uv": [10.5, 0], "uv_size": [0.5, 57]},
								"south": {"uv": [22, 0], "uv_size": [-11, 57]},
								"west": {"uv": [10.5, 0], "uv_size": [0.5, 57]},
								"up": {"uv": [11, 0.5], "uv_size": [11, -0.5]},
								"down": {"uv": [12, 1], "uv_size": [0, 0]}
							}
						}
					]
				},
				{
					"name": "legr1",
					"parent": "torso",
					"pivot": [-5.24495, 41.12749, -1.4032],
					"cubes": [
						{"origin": [-16.05, 37.2236, -0.26809], "size": [8.725, 3.55, 2.85], "pivot": [-1.9, 38.6611, 0.11941], "rotation": [-23.6424, -26.7021, 39.899], "uv": [0, 57]},
						{"origin": [-20.35745, 48.92749, -10.2282], "size": [9.125, 1.65, 1.45], "pivot": [-17.79495, 43.15249, -9.5032], "rotation": [-11.644, -33.325, 16.2077], "uv": [72, 4]}
					]
				},
				{
					"name": "joint1",
					"parent": "legr1",
					"pivot": [-18.46995, 49.47749, -9.8532],
					"cubes": [
						{"origin": [-30.55745, 49.02749, -7.5532], "size": [10.725, 0.525, 1.125], "pivot": [-17.79495, 43.15249, -9.5032], "rotation": [63.0335, -52.5186, -128.5029], "uv": [67, 63]},
						{"origin": [-23.45745, 47.02749, -10.2282], "size": [10.725, 2.65, 1.45], "pivot": [-17.79495, 43.15249, -9.5032], "rotation": [29.5815, -19.7744, -63.5583], "uv": [56, 46]}
					]
				},
				{
					"name": "legr2",
					"parent": "torso",
					"pivot": [-2.85576, 36.65674, -1.55193],
					"rotation": [-5.03021, 45.64478, -26.06999],
					"cubes": [
						{"origin": [-16.04395, 35.39838, -3.25904], "size": [12.975, 2.025, 2.85], "pivot": [-1.89395, 35.31088, -2.87154], "rotation": [-23.6424, -26.7021, 39.899], "uv": [44, 14]},
						{"origin": [-20.3514, 45.57728, -13.21915], "size": [9.125, 1.65, 1.45], "pivot": [-17.7889, 39.80228, -12.49415], "rotation": [-11.644, -33.325, 16.2077], "uv": [70, 31]}
					]
				},
				{
					"name": "joint4",
					"parent": "legr2",
					"pivot": [-18.8889, 46.60228, -12.89415],
					"cubes": [
						{"origin": [-30.5514, 45.67728, -10.54415], "size": [10.725, 0.525, 1.125], "pivot": [-17.7889, 39.80228, -12.49415], "rotation": [63.0335, -52.5186, -128.5029], "uv": [65, 60]},
						{"origin": [-23.4514, 43.67728, -13.21915], "size": [10.725, 2.65, 1.45], "pivot": [-17.7889, 39.80228, -12.49415], "rotation": [29.5815, -19.7744, -63.5583], "uv": [56, 40]}
					]
				},
				{
					"name": "legr3",
					"parent": "torso",
					"pivot": [-3.43076, 36.63174, -1.00193],
					"cubes": [
						{"origin": [-16.51826, 29.50674, 7.97307], "size": [9.125, 1.65, 1.45], "pivot": [-13.95576, 23.73174, 8.69807], "rotation": [37.4209, 17.8836, -42.3763], "uv": [70, 10]},
						{"origin": [-14.38959, 35.38596, 1.71553], "size": [12.975, 2.025, 2.85], "pivot": [-0.23959, 35.29846, 2.10303], "rotation": [40.7219, 4.2305, -25.4065], "uv": [44, 10]}
					]
				},
				{
					"name": "joint6",
					"parent": "legr3",
					"pivot": [-19.68076, 24.65674, 6.19807],
					"cubes": [
						{"origin": [-26.71826, 29.60674, 10.64807], "size": [10.725, 0.525, 1.125], "pivot": [-13.95576, 23.73174, 8.69807], "rotation": [-17.4811, -18.9311, -124.6787], "uv": [54, 26]},
						{"origin": [-19.61826, 27.60674, 7.97307], "size": [10.725, 2.65, 1.45], "pivot": [-13.95576, 23.73174, 8.69807], "rotation": [-7.6915, 40.2988, -122.303], "uv": [55, 23]}
					]
				},
				{
					"name": "pincerR",
					"parent": "torso",
					"pivot": [-3.025, 43.2361, -2.20559],
					"cubes": [
						{"origin": [-19.49294, 49.31858, -16.25763], "size": [8.825, 3.55, 2.85], "pivot": [-15.38044, 56.09358, -14.13263], "rotation": [3.42716, -61.3696, -0.84846], "uv": [55, 18]},
						{"origin": [-24.39294, 49.61858, -14.55763], "size": [6.225, 6.05, 2.475], "pivot": [-15.38044, 56.09358, -14.13263], "rotation": [44.61646, -70.00743, -47.52611], "uv": [66, 52]},
						{"origin": [-21.24294, 47.86858, -14.55763], "size": [6.8, 6.05, 2.75], "pivot": [-15.38044, 54.34358, -14.13263], "rotation": [-37.66478, -75.42605, 47.08376], "uv": [0, 62]},
						{"origin": [-30.36794, 54.41858, -13.85763], "size": [6.225, 1.25, 0.675], "pivot": [-15.38044, 56.09358, -14.13263], "rotation": [68.36908, -62.73146, -72.84217], "uv": [73, 84]},
						{"origin": [-21.28241, 46.74986, -29.82], "size": [6.225, 0.725, 0.375], "pivot": [-18.16991, 47.11236, -29.2825], "rotation": [84.68837, -64.67619, -91.01276], "uv": [10, 80]},
						{"origin": [-20.45, 38.6236, 0.73191], "size": [15.625, 2.45, 1.85], "pivot": [0.6, 38.9611, 0.11941], "rotation": [-25.894, -34.8787, 44.2848], "uv": [44, 0]},
						{"origin": [-30.36794, 51.84358, -13.85763], "size": [6.225, 1.25, 0.675], "pivot": [-15.38044, 56.09358, -14.13263], "rotation": [64.29363, -67.08505, -68.34569], "uv": [84, 70]},
						{"origin": [-21.21675, 46.12136, -29.94213], "size": [6.225, 0.6, 0.425], "pivot": [-18.10425, 46.42136, -29.35463], "rotation": [85.52512, -71.12392, -90.87803], "uv": [17, 68]}
					]
				},
				{
					"name": "wingr",
					"parent": "torso",
					"pivot": [1.9, 44.4111, 0.91941],
					"cubes": [
						{
							"origin": [0.67552, -29.30142, 0.26274],
							"size": [16.35, 75.725, 0.3],
							"pivot": [2, 45.8111, 0.86941],
							"rotation": [58.64334, 29.78836, 27.95214],
							"uv": {
								"north": {"uv": [22, 0], "uv_size": [-11, 57]},
								"east": {"uv": [11, 0], "uv_size": [-0.5, 57]},
								"south": {"uv": [11, 0], "uv_size": [11, 57]},
								"west": {"uv": [11, 0], "uv_size": [-0.5, 57]},
								"up": {"uv": [22, 0.5], "uv_size": [-11.5, -0.5]},
								"down": {"uv": [11, 1.5], "uv_size": [2, -0.5]}
							}
						}
					]
				},
				{
					"name": "legl1",
					"parent": "torso",
					"pivot": [4.89495, 41.10249, -1.5282],
					"cubes": [
						{"origin": [7.325, 37.2236, -0.26809], "size": [8.725, 3.55, 2.85], "pivot": [1.9, 38.6611, 0.11941], "rotation": [-23.64237, 26.70211, -39.89903], "uv": [20, 57]},
						{"origin": [11.23245, 48.92749, -10.2282], "size": [9.125, 1.65, 1.45], "pivot": [17.79495, 43.15249, -9.5032], "rotation": [-11.644, 33.325, -16.2077], "uv": [72, 7]}
					]
				},
				{
					"name": "joint2",
					"parent": "legl1",
					"pivot": [18.99495, 50.07749, -10.0532],
					"cubes": [
						{"origin": [19.83245, 49.02749, -7.5532], "size": [10.725, 0.525, 1.125], "pivot": [17.79495, 43.15249, -9.5032], "rotation": [63.03348, 52.51855, 128.50294], "uv": [67, 62]},
						{"origin": [12.73245, 47.02749, -10.2282], "size": [10.725, 2.65, 1.45], "pivot": [17.79495, 43.15249, -9.5032], "rotation": [29.58153, 19.7744, 63.55831], "uv": [56, 49]}
					]
				},
				{
					"name": "legl2",
					"parent": "torso",
					"pivot": [3.55794, 37.93907, -2.85713],
					"rotation": [0, -49, 21],
					"cubes": [
						{"origin": [4.27653, 35.99753, -4.37405], "size": [13.475, 1.55, 2.85], "pivot": [3.60153, 35.43503, -3.98655], "rotation": [-23.64237, 26.70211, -39.89903], "uv": [44, 7]},
						{"origin": [12.93398, 45.70142, -14.33417], "size": [9.125, 1.65, 1.45], "pivot": [19.49648, 39.92642, -13.60917], "rotation": [-11.64398, 33.32499, -16.20765], "uv": [70, 33]}
					]
				},
				{
					"name": "joint3",
					"parent": "legl2",
					"pivot": [20.27148, 46.67642, -14.25917],
					"cubes": [
						{"origin": [21.53398, 45.80142, -11.65917], "size": [10.725, 0.525, 1.125], "pivot": [19.49648, 39.92642, -13.60917], "rotation": [63.03348, 52.51855, 128.50294], "uv": [67, 61]},
						{"origin": [14.43398, 43.80142, -14.33417], "size": [10.725, 2.65, 1.45], "pivot": [19.49648, 39.92642, -13.60917], "rotation": [29.58153, 19.7744, 63.55831], "uv": [56, 43]}
					]
				},
				{
					"name": "legl3",
					"parent": "torso",
					"pivot": [2.93294, 36.11407, 0.51787],
					"rotation": [58.25, -49, 21],
					"cubes": [
						{"origin": [3.50096, 33.54029, 0.09459], "size": [13.475, 1.55, 2.85], "pivot": [2.82596, 32.97779, 0.48209], "rotation": [-23.64237, 26.70211, -39.89903], "uv": [44, 4]},
						{"origin": [12.15841, 43.24418, -9.86553], "size": [9.125, 1.65, 1.45], "pivot": [18.72091, 37.46918, -9.14053], "rotation": [-11.64398, 33.32499, -16.20765], "uv": [70, 14]}
					]
				},
				{
					"name": "joint5",
					"parent": "legl3",
					"pivot": [20.51986, 43.73907, -10.038],
					"cubes": [
						{"origin": [13.65841, 41.34418, -9.86553], "size": [10.725, 2.65, 1.45], "pivot": [18.72091, 37.46918, -9.14053], "rotation": [29.58153, 19.7744, 63.55831], "uv": [55, 28]},
						{"origin": [20.75841, 43.34418, -7.19053], "size": [10.725, 0.525, 1.125], "pivot": [18.72091, 37.46918, -9.14053], "rotation": [63.03348, 52.51855, 128.50294], "uv": [63, 27]}
					]
				},
				{
					"name": "pelvis",
					"parent": "torso",
					"pivot": [-0.275, 36.1111, 0.66941],
					"cubes": [
						{"origin": [-5.69181, 17.52079, -1.03587], "size": [7.85, 1.65, 0.85], "pivot": [-1.76681, 18.34579, -0.61087], "rotation": [4.50036, -34.82467, -12.2004], "uv": [76, 23]},
						{"origin": [-4.775, 22.4736, -1.69309], "size": [7.15, 4.925, 2.575], "pivot": [-1.9, 25.8861, -0.40559], "rotation": [-9.25, -35, 0], "uv": [66, 65]},
						{"origin": [-3.8, 11.5736, -1.49309], "size": [5.875, 11.325, 1.7], "pivot": [-1.1, 17.1361, -0.25559], "rotation": [-2.5, -35, 0], "uv": [51, 67]},
						{"origin": [-2.075, 11.5736, -1.49309], "size": [5.6, 13.125, 1.7], "pivot": [1.1, 17.1361, -0.25559], "rotation": [-2.5, 35, 0], "uv": [44, 40]},
						{"origin": [-2.275, 22.3986, -1.69309], "size": [6.55, 5, 2.575], "pivot": [2, 25.8861, -0.40559], "rotation": [-9.25, 35, 0], "uv": [63, 71]},
						{"origin": [-2.11064, 17.24587, -0.88126], "size": [7.3, 1.625, 0.85], "pivot": [1.53936, 18.05837, -0.45626], "rotation": [4.50036, 34.82467, 12.2004], "uv": [76, 3]},
						{"origin": [-2.55, 27.0236, -0.64309], "size": [5.725, 10.55, 1.35], "pivot": [-1.375, 27.1111, -0.25559], "rotation": [-2.5, -35, 0], "uv": [32, 68]},
						{"origin": [-3.175, 27.0236, -0.64309], "size": [5.575, 9.55, 1.35], "pivot": [1.375, 27.1111, -0.25559], "rotation": [-2.5, 35, 0], "uv": [18, 70]},
						{"origin": [-4.175, 32.4486, 0.25691], "size": [7.575, 1.05, 1.35], "pivot": [1.375, 24.9361, 0.64441], "rotation": [-2.04834, -1.47342, 1.48724], "uv": [17, 70]},
						{"origin": [-4.175, 28.7986, 0.25691], "size": [7.575, 1.05, 1.35], "pivot": [1.375, 21.2861, 0.64441], "rotation": [-2.04834, -1.47342, 1.48724], "uv": [17, 70]}
					]
				},
				{
					"name": "tail",
					"parent": "pelvis",
					"pivot": [0, 16.2861, -0.25559]
				},
				{
					"name": "tail1",
					"parent": "tail",
					"pivot": [-1.1, 9.5861, -0.25559],
					"cubes": [
						{"origin": [-2.075, 13.6736, -1.49309], "size": [8.125, 1.075, 1.7], "pivot": [1.1, 10.4861, -0.25559], "rotation": [0.65679, 35.07245, 5.4959], "uv": [72, 12]},
						{"origin": [-1.575, 12.2486, -1.24309], "size": [6.6, 1.6, 1.2], "pivot": [1.1, 9.5861, -0.25559], "rotation": [-2.5, 35, 0], "uv": [82, 53]},
						{"origin": [-5.95, 13.5486, -1.49309], "size": [7.425, 1.2, 1.7], "pivot": [-1.1, 10.4861, -0.25559], "rotation": [1.18318, -35.0604, -6.41211], "uv": [75, 20]},
						{"origin": [-5.225, 12.0486, -1.24309], "size": [6.8, 1.8, 1.2], "pivot": [-1.1, 9.5861, -0.25559], "rotation": [-2.5, -35, 0], "uv": [63, 80]}
					]
				},
				{
					"name": "tail2",
					"parent": "tail",
					"pivot": [1.1, 7.6861, -0.25559],
					"cubes": [
						{"origin": [-1.825, 11.6236, -1.49309], "size": [7.725, 0.8, 1.7], "pivot": [1.1, 8.5861, -0.25559], "rotation": [-0.92302, 35.06722, 2.74673], "uv": [74, 22]},
						{"origin": [-1.325, 10.0986, -1.24309], "size": [5.65, 1.85, 1.2], "pivot": [1.1, 7.6861, -0.25559], "rotation": [-2.5, 35, 0], "uv": [84, 68]},
						{"origin": [-5.85, 11.6236, -1.49309], "size": [7.65, 0.8, 1.7], "pivot": [-1.1, 8.4361, -0.25559], "rotation": [2.23459, -35.01567, -8.24334], "uv": [73, 9]},
						{"origin": [-4.45, 10.2736, -1.24309], "size": [5.75, 1.675, 1.2], "pivot": [-1.1, 7.6861, -0.25559], "rotation": [-2.5, -35, 0], "uv": [84, 66]}
					]
				},
				{
					"name": "tail7",
					"parent": "tail",
					"pivot": [1.1, 5.6111, -0.95559],
					"rotation": [-7.25, 0, 0],
					"cubes": [
						{"origin": [-1.8, 9.5986, -2.19309], "size": [7.525, 0.75, 1.7], "pivot": [1.1, 6.5111, -0.95559], "rotation": [1.35857, 35.05486, 6.71745], "uv": [73, 6]},
						{"origin": [-0.975, 4.9986, -1.94309], "size": [4.525, 4.875, 1.2], "pivot": [1.1, 5.6111, -0.95559], "rotation": [-2.5, 35, 0], "uv": [63, 82]},
						{"origin": [-5.75, 9.5736, -2.19309], "size": [7.425, 0.75, 1.7], "pivot": [-1.1, 6.5111, -0.95559], "rotation": [1.5339, -35.04855, -7.02274], "uv": [67, 64]},
						{"origin": [-3.6, 4.6236, -1.94309], "size": [4.55, 5.25, 1.2], "pivot": [-1.1, 5.6111, -0.95559], "rotation": [-2.5, -35, 0], "uv": [53, 79]}
					]
				},
				{
					"name": "tail3",
					"parent": "tail",
					"pivot": [-1.1, 11.5861, -0.25559],
					"cubes": [
						{"origin": [-1.825, 14.5986, -1.24309], "size": [6.625, 1.25, 1.2], "pivot": [1.1, 11.5861, -0.25559], "rotation": [-2.5, 35, 0], "uv": [62, 78]},
						{"origin": [-4.775, 14.5986, -1.24309], "size": [6.6, 1.25, 1.2], "pivot": [-1.1, 11.5861, -0.25559], "rotation": [-2.5, -35, 0], "uv": [77, 71]}
					]
				},
				{
					"name": "segment2",
					"parent": "tail",
					"pivot": [0, 5.0111, -0.85559]
				},
				{
					"name": "tail8",
					"parent": "segment2",
					"pivot": [1.1, 0.0111, -1.95559],
					"rotation": [-12.5, 0, 0],
					"cubes": [
						{"origin": [-1.35, 3.6486, -3.19309], "size": [6.05, 1.525, 1.7], "pivot": [1.1, 0.9111, -1.95559], "rotation": [-2.5, 35, 0], "uv": [80, 51]},
						{"origin": [-1.025, 2.7486, -2.94309], "size": [5, 1.525, 1.2], "pivot": [1.1, 0.0111, -1.95559], "rotation": [-2.5, 35, 0], "uv": [0, 84]},
						{"origin": [-4.75, 3.6486, -3.19309], "size": [6.125, 1.525, 1.7], "pivot": [-1.1, 0.9111, -1.95559], "rotation": [-2.5, -35, 0], "uv": [79, 73]},
						{"origin": [-3.85, 2.6986, -2.94309], "size": [4.825, 1.575, 1.2], "pivot": [-1.1, 0.0111, -1.95559], "rotation": [-2.5, -35, 0], "uv": [73, 85]}
					]
				},
				{
					"name": "tail9",
					"parent": "segment2",
					"pivot": [1.1, -2.3889, -1.95559],
					"rotation": [-12.5, 0, 0],
					"cubes": [
						{"origin": [-1.225, 1.7736, -3.71809], "size": [5.975, 1, 1.7], "pivot": [1.1, -1.4889, -2.48059], "rotation": [1.35857, 35.05486, 6.71745], "uv": [82, 64]},
						{"origin": [-0.975, 1.1486, -3.46809], "size": [4.65, 0.725, 1.2], "pivot": [1.1, -2.3889, -2.48059], "rotation": [-2.5, 35, 0], "uv": [86, 25]},
						{"origin": [-4.65, 1.7736, -3.71809], "size": [5.975, 1, 1.7], "pivot": [-1.1, -1.4889, -2.48059], "rotation": [2.05952, -35.02503, -7.93828], "uv": [56, 52]},
						{"origin": [-3.725, 0.8736, -3.46809], "size": [4.775, 1, 1.2], "pivot": [-1.1, -2.3889, -2.48059], "rotation": [-2.5, -35, 0], "uv": [51, 85]}
					]
				},
				{
					"name": "tail4",
					"parent": "segment2",
					"pivot": [1.1, -3.7639, -1.95559],
					"rotation": [-12.5, 0, 0],
					"cubes": [
						{"origin": [-0.775, 0.3986, -3.71809], "size": [5.4, 0.775, 1.7], "pivot": [1.1, -2.8639, -2.48059], "rotation": [-2.5, 35, 0], "uv": [85, 40]},
						{"origin": [-0.95, -4.4014, -3.46809], "size": [3.925, 4.9, 1.2], "pivot": [1.1, -3.7639, -2.48059], "rotation": [-2.5, 35, 0], "uv": [43, 85]},
						{"origin": [-4.625, 0.3986, -3.71809], "size": [5.45, 0.725, 1.7], "pivot": [-1.1, -2.8639, -2.48059], "rotation": [-2.5, -35, 0], "uv": [56, 70]},
						{"origin": [-2.975, -4.4014, -3.46809], "size": [4.075, 4.9, 1.2], "pivot": [-1.1, -3.7639, -2.48059], "rotation": [-2.5, -35, 0], "uv": [82, 55]}
					]
				},
				{
					"name": "segment3",
					"parent": "segment2",
					"pivot": [0, -4.2639, -2.35559]
				},
				{
					"name": "tail10",
					"parent": "segment3",
					"pivot": [1.1, -12.1639, -3.95559],
					"rotation": [-21.75, 0, 0],
					"cubes": [
						{"origin": [-1.15, -8.4514, -5.71809], "size": [4.225, 0.7, 1.7], "pivot": [1.1, -12.0139, -4.48059], "rotation": [-2.5, 35, 0], "uv": [75, 30]},
						{"origin": [-1.025, -14.6264, -5.46809], "size": [3.175, 6.8, 1.2], "pivot": [1.1, -11.8639, -4.48059], "rotation": [-2.5, 35, 0], "uv": [18, 80]},
						{"origin": [-3.075, -8.4514, -5.71809], "size": [4.275, 0.7, 1.7], "pivot": [-1.1, -12.0139, -4.48059], "rotation": [-2.5, -35, 0], "uv": [69, 28]},
						{"origin": [-2.3, -14.6014, -5.46809], "size": [3.375, 6.7, 1.2], "pivot": [-1.1, -11.8389, -4.48059], "rotation": [-2.5, -35, 0], "uv": [44, 18]}
					]
				},
				{
					"name": "tail6",
					"parent": "segment3",
					"pivot": [1.1, -11.0889, -2.68059],
					"rotation": [-12.5, 0, 0],
					"cubes": [
						{"origin": [-0.9, -6.6264, -4.44309], "size": [4.975, 0.7, 1.7], "pivot": [1.1, -10.1889, -3.20559], "rotation": [-2.5, 35, 0], "uv": [8, 86]},
						{"origin": [-1, -7.2764, -4.19309], "size": [4.725, 0.75, 1.2], "pivot": [1.1, -10.7889, -3.20559], "rotation": [-2.5, 35, 0], "uv": [0, 86]},
						{"origin": [-1.125, -8.1514, -4.19309], "size": [4.125, 1, 0.975], "pivot": [1.1, -11.4139, -3.20559], "rotation": [-2.5, 35, 0], "uv": [51, 87]},
						{"origin": [-4.075, -6.6264, -4.44309], "size": [4.95, 0.7, 1.7], "pivot": [-1.1, -10.1889, -3.20559], "rotation": [-2.5, -35, 0], "uv": [68, 61]},
						{"origin": [-3.775, -7.3014, -4.19309], "size": [4.9, 0.8, 1.2], "pivot": [-1.1, -10.7639, -3.20559], "rotation": [-2.5, -35, 0], "uv": [85, 41]},
						{"origin": [-3.25, -8.0264, -4.09309], "size": [4.275, 1.525, 0.95], "pivot": [-1.1, -10.7639, -3.20559], "rotation": [-2.5, -35, 0], "uv": [65, 87]}
					]
				},
				{
					"name": "tail5",
					"parent": "segment3",
					"pivot": [1.1, -9.5139, -2.53059],
					"rotation": [-12.5, 0, 0],
					"cubes": [
						{"origin": [-0.775, -5.0514, -4.29309], "size": [5.1, 0.7, 1.7], "pivot": [1.1, -8.6139, -3.05559], "rotation": [-2.5, 35, 0], "uv": [88, 76]},
						{"origin": [-0.95, -5.8764, -4.04309], "size": [4.925, 0.925, 1.2], "pivot": [1.1, -9.2139, -3.05559], "rotation": [-2.5, 35, 0], "uv": [86, 24]},
						{"origin": [-4.325, -5.0514, -4.29309], "size": [5.15, 0.7, 1.7], "pivot": [-1.1, -8.6139, -3.05559], "rotation": [-2.5, -35, 0], "uv": [66, 82]},
						{"origin": [-4.025, -5.8764, -4.04309], "size": [5.125, 0.95, 1.2], "pivot": [-1.1, -9.1889, -3.05559], "rotation": [-2.5, -35, 0], "uv": [55, 63]}
					]
				},
				{
					"name": "segment4",
					"parent": "segment3",
					"pivot": [0, -13.79066, -5.32576]
				},
				{
					"name": "tail12",
					"parent": "segment4",
					"pivot": [0, -15.89066, -7.02576],
					"rotation": [-44.25, 0, 0],
					"cubes": [
						{"origin": [-1.025, -15.5792, -7.75826], "size": [3.875, 0.7, 1.325], "pivot": [0.875, -19.1417, -6.89576], "rotation": [-2.5, 35, 0], "uv": [54, 63]},
						{"origin": [-1.225, -18.5792, -7.50826], "size": [3.55, 3.1, 0.825], "pivot": [0.9, -19.7417, -6.89576], "rotation": [-2.5, 35, 0], "uv": [16, 87]},
						{"origin": [-2.725, -15.5792, -7.75826], "size": [3.875, 0.7, 1.325], "pivot": [-0.75, -19.1417, -6.89576], "rotation": [-2.5, -35, 0], "uv": [54, 65]},
						{"origin": [-2.075, -18.5792, -7.50826], "size": [3.625, 3.125, 0.825], "pivot": [-0.625, -19.7167, -6.89576], "rotation": [-2.5, -35, 0], "uv": [57, 71]}
					]
				},
				{
					"name": "tail13",
					"parent": "segment4",
					"pivot": [0, -17.52024, -8.61324],
					"rotation": [-46.5, 0, 0],
					"cubes": [
						{"origin": [-0.725, -17.20879, -9.34574], "size": [3.275, 0.7, 1.325], "pivot": [0.875, -20.77129, -8.48324], "rotation": [-2.5, 35, 0], "uv": [53, 66]},
						{"origin": [-2.425, -17.20879, -9.34574], "size": [3.275, 0.7, 1.325], "pivot": [-0.75, -20.77129, -8.48324], "rotation": [-2.5, -35, 0], "uv": [25, 71]}
					]
				},
				{
					"name": "tail11",
					"parent": "segment4",
					"pivot": [0, -14.66566, -5.95076],
					"rotation": [-30.75, 0, 0],
					"cubes": [
						{"origin": [-0.8, -14.3542, -7.05826], "size": [3.875, 0.7, 1.7], "pivot": [1.1, -17.9167, -5.82076], "rotation": [-2.5, 35, 0], "uv": [26, 75]},
						{"origin": [-1.025, -15.5792, -6.80826], "size": [3.55, 1.325, 1.2], "pivot": [1.1, -18.5167, -5.82076], "rotation": [-2.5, 35, 0], "uv": [8, 87]},
						{"origin": [-3.075, -14.3542, -7.05826], "size": [3.875, 0.7, 1.7], "pivot": [-1.1, -17.9167, -5.82076], "rotation": [-2.5, -35, 0], "uv": [26, 69]},
						{"origin": [-2.55, -15.5792, -6.80826], "size": [3.625, 1.35, 1.2], "pivot": [-1.1, -18.4917, -5.82076], "rotation": [-2.5, -35, 0], "uv": [0, 87]}
					]
				},
				{
					"name": "stinger",
					"parent": "segment4",
					"pivot": [0, -18.30324, -9.28923],
					"rotation": [-11, 0, 0],
					"cubes": [
						{"origin": [-1.075, -30.07824, -14.58923], "size": [2.15, 4.6, 1.775], "pivot": [0, -27.30324, -2.08923], "rotation": [-42.25, 0, 0], "uv": [44, 68]},
						{"origin": [-0.55, -26.77824, -14.06423], "size": [1.1, 4.6, 0.725], "pivot": [0, -27.30324, -2.08923], "rotation": [-42.25, 0, 0], "uv": [30, 67]},
						{"origin": [-1.5, -28.95324, -13.98923], "size": [3, 2.95, 0.8], "pivot": [0, -27.30324, -2.08923], "rotation": [-42.25, 0, 0], "uv": [22, 87]},
						{"origin": [-1.925, -20.46582, -12.01961], "size": [3.85, 1.475, 2.4], "pivot": [0, -19.72832, -10.74461], "rotation": [-33, 0, 0], "uv": [83, 84]},
						{"origin": [-0.325, -38.90324, -11.58923], "size": [0.65, 4.275, 0.675], "pivot": [0, -27.30324, -2.08923], "rotation": [-71, 0, 0], "uv": [55, 5]},
						{"origin": [-0.7, -36.75324, -11.71423], "size": [1.4, 2.125, 1.15], "pivot": [0, -27.30324, -2.08923], "rotation": [-71, 0, 0], "uv": [58, 31]},
						{"origin": [-0.1, -44.80324, -6.43923], "size": [0.2, 3.475, 0.325], "pivot": [0, -27.30324, -2.08923], "rotation": [-93, 0, 0], "uv": [59, 21]}
					]
				},
				{
					"name": "head",
					"parent": "full",
					"pivot": [0, 45.9611, -0.03059],
					"rotation": [27.25, 0, 0],
					"cubes": [
						{"origin": [-2.85, 52.47652, -3.71443], "size": [4.9, 5.55, 4.9], "pivot": [-0.475, 52.56402, -0.67693], "rotation": [-32.37999, -41.7736, 23.74683], "uv": [36, 59]},
						{
							"origin": [-3.775, 54.10152, -2.81443],
							"size": [3.25, 4.125, 4.45],
							"pivot": [-0.475, 52.56402, -0.67693],
							"rotation": [-9.9683, -50.24704, -6.96378],
							"uv": {
								"north": {"uv": [60.5, 87], "uv_size": [3, 3]},
								"east": {"uv": [58, 87], "uv_size": [2, 3]},
								"south": {"uv": [66, 87], "uv_size": [3, 3]},
								"west": {"uv": [64, 87], "uv_size": [2, 3]},
								"up": {"uv": [61, 85], "uv_size": [3, 2]},
								"down": {"uv": [63.5, 90], "uv_size": [3, -2]}
							}
						},
						{
							"origin": [-3.97217, 55.23955, -1.70871],
							"size": [3.225, 2.175, 3.6],
							"pivot": [-0.475, 52.56402, -0.67693],
							"rotation": [-9.9683, -50.24704, -6.96378],
							"uv": {
								"north": {"uv": [60.5, 87], "uv_size": [3, 3]},
								"east": {"uv": [58, 87], "uv_size": [2, 3]},
								"south": {"uv": [66, 87], "uv_size": [3, 3]},
								"west": {"uv": [64, 87], "uv_size": [2, 3]},
								"up": {"uv": [61, 85], "uv_size": [3, 2]},
								"down": {"uv": [63, 90], "uv_size": [3, -2]}
							}
						},
						{
							"origin": [-2.24717, 57.16455, 1.11629],
							"size": [2.525, 2.3, 0.775],
							"pivot": [0.55, 54.48902, -0.67693],
							"rotation": [-0.85499, -50.95762, -18.74006],
							"uv": {
								"north": {"uv": [60.5, 87], "uv_size": [3, 3]},
								"east": {"uv": [58, 87], "uv_size": [2, 3]},
								"south": {"uv": [66, 87], "uv_size": [3, 3]},
								"west": {"uv": [64, 87], "uv_size": [2, 3]},
								"up": {"uv": [61, 85], "uv_size": [3, 2]},
								"down": {"uv": [64, 87], "uv_size": [3, -2]}
							}
						},
						{"origin": [-2.075, 53.65152, -2.93943], "size": [3.35, 5.325, 3.35], "pivot": [-0.475, 54.26402, -0.67693], "rotation": [-32.37999, -41.7736, 23.74683], "uv": [41, 76]},
						{
							"origin": [-2.975, 48.02652, -2.63943],
							"size": [4.45, 9.3, 4.2],
							"pivot": [-0.675, 50.76402, 0.04807],
							"rotation": [-6.29675, -47.73099, 7.02185],
							"uv": {
								"north": {"uv": [117, 3], "uv_size": [4, 9]},
								"east": {"uv": [114, 3], "uv_size": [3, 9]},
								"south": {"uv": [124, 3], "uv_size": [4, 9]},
								"west": {"uv": [121, 3], "uv_size": [3, 9]},
								"up": {"uv": [117, 0], "uv_size": [4, 3]},
								"down": {"uv": [121, 3], "uv_size": [4, -3]}
							}
						},
						{"origin": [-2.66003, 45.61119, -2.57417], "size": [3.125, 5.275, 2.625], "pivot": [-0.475, 50.76402, 0.04807], "rotation": [-35.0219, -41.43972, 25.04691], "uv": [118, 10]},
						{"origin": [-1.86234, 44.21098, -1.85229], "size": [2.025, 2.1, 1.775], "pivot": [-0.475, 50.76402, 0.04807], "rotation": [-35.0219, -41.43972, 25.04691], "uv": [122, 17]},
						{"origin": [-1.20353, 41.81856, -1.21739], "size": [2.5, 10.075, 2.125], "pivot": [0, 46.93902, 0.44807], "rotation": [-8.04834, -1.47342, 1.48724], "uv": [12, 75]},
						{"origin": [-0.575, 45.47652, -0.41443], "size": [1.15, 8.95, 2], "pivot": [0, 46.93902, 0.47307], "rotation": [8.70166, -1.47342, 1.48724], "uv": [28, 78]},
						{
							"origin": [0.425, 54.20152, -2.81443],
							"size": [3.3, 4.075, 4.375],
							"pivot": [0.475, 52.56402, -0.67693],
							"rotation": [-9.9683, 50.24704, 6.96378],
							"uv": {
								"north": {"uv": [35, 81], "uv_size": [2.5, 3]},
								"east": {"uv": [33, 81], "uv_size": [2, 3]},
								"south": {"uv": [40, 81], "uv_size": [3, 3]},
								"west": {"uv": [37.5, 81], "uv_size": [1.5, 3]},
								"up": {"uv": [35, 79], "uv_size": [3, 2]},
								"down": {"uv": [38, 81], "uv_size": [3, -2]}
							}
						},
						{
							"origin": [0.87869, 55.19154, -1.81341],
							"size": [3.1, 2.375, 3.6],
							"pivot": [0.475, 52.56402, -0.67693],
							"rotation": [-9.9683, 50.24704, 6.96378],
							"uv": {
								"north": {"uv": [35, 81], "uv_size": [2.5, 3]},
								"east": {"uv": [33, 81], "uv_size": [2, 3]},
								"south": {"uv": [40, 81], "uv_size": [3, 3]},
								"west": {"uv": [37.5, 81], "uv_size": [1.5, 3]},
								"up": {"uv": [35, 79], "uv_size": [3, 2]},
								"down": {"uv": [38, 81], "uv_size": [3, -2]}
							}
						},
						{"origin": [-2.05, 52.47652, -3.71443], "size": [4.9, 5.55, 4.9], "pivot": [0.475, 52.56402, -0.67693], "rotation": [-32.37999, 41.7736, -23.74683], "uv": [58, 31]},
						{"origin": [-1.275, 53.65152, -2.93943], "size": [3.35, 5.325, 3.35], "pivot": [0.475, 54.26402, -0.67693], "rotation": [-32.37999, 41.7736, -23.74683], "uv": [0, 75]},
						{
							"origin": [-0.27783, 57.16455, 1.11629],
							"size": [2.525, 2.3, 0.775],
							"pivot": [-0.55, 54.48902, -0.67693],
							"rotation": [-0.85499, 50.95762, 18.74006],
							"uv": {
								"north": {"uv": [63.5, 87], "uv_size": [-3, 3]},
								"east": {"uv": [66, 87], "uv_size": [-2, 3]},
								"south": {"uv": [69, 87], "uv_size": [-3, 3]},
								"west": {"uv": [60, 87], "uv_size": [-2, 3]},
								"up": {"uv": [64, 85], "uv_size": [-3, 2]},
								"down": {"uv": [67, 87], "uv_size": [-3, -2]}
							}
						},
						{
							"origin": [0.525, 54.10152, -2.81443],
							"size": [3.25, 4.125, 4.45],
							"pivot": [0.475, 52.56402, -0.67693],
							"rotation": [-9.9683, 50.24704, 6.96378],
							"uv": {
								"north": {"uv": [63.5, 87], "uv_size": [-3, 3]},
								"east": {"uv": [66, 87], "uv_size": [-2, 3]},
								"south": {"uv": [69, 87], "uv_size": [-3, 3]},
								"west": {"uv": [60, 87], "uv_size": [-2, 3]},
								"up": {"uv": [64, 85], "uv_size": [-3, 2]},
								"down": {"uv": [66.5, 90], "uv_size": [-3, -2]}
							}
						},
						{
							"origin": [0.74717, 55.23955, -1.70871],
							"size": [3.225, 2.175, 3.6],
							"pivot": [0.475, 52.56402, -0.67693],
							"rotation": [-9.9683, 50.24704, 6.96378],
							"uv": {
								"north": {"uv": [63.5, 87], "uv_size": [-3, 3]},
								"east": {"uv": [66, 87], "uv_size": [-2, 3]},
								"south": {"uv": [69, 87], "uv_size": [-3, 3]},
								"west": {"uv": [60, 87], "uv_size": [-2, 3]},
								"up": {"uv": [64, 85], "uv_size": [-3, 2]},
								"down": {"uv": [66, 90], "uv_size": [-3, -2]}
							}
						}
					]
				},
				{
					"name": "suckler",
					"parent": "head",
					"pivot": [0, 48.28634, -5.20565],
					"rotation": [112.5, 0, 0],
					"cubes": [
						{"origin": [-0.275, 49.70912, -27.76658], "size": [0.55, 0.6, 7.95], "pivot": [0, 42.11606, -14.28152], "rotation": [-63.75, 0, 0], "uv": [-2, 74]},
						{"origin": [-0.6, 45.91118, -10.03733], "size": [1.2, 1.025, 9.55], "pivot": [0, 48.28634, -5.20565], "rotation": [-48.75, 0, 0], "uv": [108, 17]}
					]
				}
			]
		}
	]
}